{
  "actor_name": "Люк Бессон",
  "actor_href": "https://www.kinopoisk.ru/name/24505/",
  "films": [
    {
      "film_name": "Флора Плам",
      "film_href": "https:/www.kinopoisk.ru/film/409270/"
    },
    {
      "film_name": "Люси 2",
      "film_href": "https:/www.kinopoisk.ru/film/919461/"
    },
    {
      "film_name": "Дважды",
      "film_href": "https:/www.kinopoisk.ru/film/911771/"
    },
    {
      "film_name": "Ruby Tuesday",
      "film_href": "https:/www.kinopoisk.ru/film/261638/"
    },
    {
      "film_name": "Colombiana 2",
      "film_href": "https:/www.kinopoisk.ru/film/955032/"
    },
    {
      "film_name": "The French Detective (ТВ)",
      "film_href": "https:/www.kinopoisk.ru/film/1108502/"
    },
    {
      "film_name": "American Flagg! (сериал, 2018 – ...)",
      "film_href": "https:/www.kinopoisk.ru/series/1115224/"
    },
    {
      "film_name": "Анна (2019)",
      "film_href": "https:/www.kinopoisk.ru/film/1049727/"
    },
    {
      "film_name": "Курск (2018)",
      "film_href": "https:/www.kinopoisk.ru/film/929027/"
    },
    {
      "film_name": "Такси 5 (2018)",
      "film_href": "https:/www.kinopoisk.ru/film/1047736/"
    },
    {
      "film_name": "Ева (2018)",
      "film_href": "https:/www.kinopoisk.ru/film/1037323/"
    },
    {
      "film_name": "Заложница: Начало (сериал, 2017 – 2018)",
      "film_href": "https:/www.kinopoisk.ru/series/982784/"
    },
    {
      "film_name": "Валериан и город тысячи планет (2017)",
      "film_href": "https:/www.kinopoisk.ru/film/689960/"
    },
    {
      "film_name": "Безбашенные (2016)",
      "film_href": "https:/www.kinopoisk.ru/film/893984/"
    },
    {
      "film_name": "Врата воинов (2016)",
      "film_href": "https:/www.kinopoisk.ru/film/909973/"
    },
    {
      "film_name": "Перевозчик: Наследие (2015)",
      "film_href": "https:/www.kinopoisk.ru/film/764608/"
    },
    {
      "film_name": "Заложница 3 (2014)",
      "film_href": "https:/www.kinopoisk.ru/film/712639/"
    },
    {
      "film_name": "Местный (2014)",
      "film_href": "https:/www.kinopoisk.ru/film/679894/"
    },
    {
      "film_name": "13-й район: Кирпичные особняки (2013)",
      "film_href": "https:/www.kinopoisk.ru/film/462667/"
    },
    {
      "film_name": "Перекрёсток (2013)",
      "film_href": "https:/www.kinopoisk.ru/film/535313/"
    },
    {
      "film_name": "Перевозчик (сериал, 2012 – 2014)",
      "film_href": "https:/www.kinopoisk.ru/series/587984/"
    },
    {
      "film_name": "Без ограничений (сериал, 2012 – ...)",
      "film_href": "https:/www.kinopoisk.ru/series/841976/"
    },
    {
      "film_name": "Заложница 2 (2012)",
      "film_href": "https:/www.kinopoisk.ru/film/453544/"
    },
    {
      "film_name": "Слепой (2012)",
      "film_href": "https:/www.kinopoisk.ru/film/660948/"
    },
    {
      "film_name": "Напролом (2011)",
      "film_href": "https:/www.kinopoisk.ru/film/496888/"
    },
    {
      "film_name": "Притон (2011)",
      "film_href": "https:/www.kinopoisk.ru/film/568365/"
    },
    {
      "film_name": "Коломбиана (2011)",
      "film_href": "https:/www.kinopoisk.ru/film/523122/"
    },
    {
      "film_name": "Халяльные полицейские страны (2011)",
      "film_href": "https:/www.kinopoisk.ru/film/565905/"
    },
    {
      "film_name": "Монстр в Париже (2010)",
      "film_href": "https:/www.kinopoisk.ru/film/279685/"
    },
    {
      "film_name": "22 пули: Бессмертный (2010)",
      "film_href": "https:/www.kinopoisk.ru/film/470658/"
    },
    {
      "film_name": "Артур и война двух миров (2010)",
      "film_href": "https:/www.kinopoisk.ru/film/278221/"
    },
    {
      "film_name": "Артур и месть Урдалака (2009)",
      "film_href": "https:/www.kinopoisk.ru/film/278222/"
    },
    {
      "film_name": "Дом. История путешествия (2009)",
      "film_href": "https:/www.kinopoisk.ru/film/309397/"
    },
    {
      "film_name": "Миссионер (2009)",
      "film_href": "https:/www.kinopoisk.ru/film/430556/"
    },
    {
      "film_name": "13-й район: Ультиматум (2009)",
      "film_href": "https:/www.kinopoisk.ru/film/418794/"
    },
    {
      "film_name": "Стейтен Айленд (2008)",
      "film_href": "https:/www.kinopoisk.ru/film/279742/"
    },
    {
      "film_name": "Я люблю тебя, Филлип Моррис (2008)",
      "film_href": "https:/www.kinopoisk.ru/film/402550/"
    },
    {
      "film_name": "Перевозчик 3 (2008)",
      "film_href": "https:/www.kinopoisk.ru/film/409159/"
    },
    {
      "film_name": "Заложница (2007)",
      "film_href": "https:/www.kinopoisk.ru/film/276376/"
    },
    {
      "film_name": "Граница (2007)",
      "film_href": "https:/www.kinopoisk.ru/film/266142/"
    },
    {
      "film_name": "Гость (2007)",
      "film_href": "https:/www.kinopoisk.ru/film/261640/"
    },
    {
      "film_name": "Мишу из Д’Обера (2007)",
      "film_href": "https:/www.kinopoisk.ru/film/195338/"
    },
    {
      "film_name": "Такси 4 (2007)",
      "film_href": "https:/www.kinopoisk.ru/film/258478/"
    },
    {
      "film_name": "Секрет (2006)",
      "film_href": "https:/www.kinopoisk.ru/film/102204/"
    },
    {
      "film_name": "Артур и минипуты (2006)",
      "film_href": "https:/www.kinopoisk.ru/film/14328/"
    },
    {
      "film_name": "Диккенек (2006)",
      "film_href": "https:/www.kinopoisk.ru/film/104981/"
    },
    {
      "film_name": "Бандитки (2006)",
      "film_href": "https:/www.kinopoisk.ru/film/81102/"
    },
    {
      "film_name": "Любовь и другие катастрофы (2005)",
      "film_href": "https:/www.kinopoisk.ru/film/102203/"
    },
    {
      "film_name": "Быть Стэнли Кубриком (2005)",
      "film_href": "https:/www.kinopoisk.ru/film/51587/"
    },
    {
      "film_name": "Ангел-А (2005)",
      "film_href": "https:/www.kinopoisk.ru/film/160929/"
    },
    {
      "film_name": "Три могилы (2005)",
      "film_href": "https:/www.kinopoisk.ru/film/81519/"
    },
    {
      "film_name": "Черный ящик (2005)",
      "film_href": "https:/www.kinopoisk.ru/film/81518/"
    },
    {
      "film_name": "Револьвер (2005)",
      "film_href": "https:/www.kinopoisk.ru/film/18973/"
    },
    {
      "film_name": "Перевозчик 2 (2005)",
      "film_href": "https:/www.kinopoisk.ru/film/77588/"
    },
    {
      "film_name": "Следующий! (2005)",
      "film_href": "https:/www.kinopoisk.ru/film/83795/"
    },
    {
      "film_name": "Обман (2005)",
      "film_href": "https:/www.kinopoisk.ru/film/14332/"
    },
    {
      "film_name": "Дэнни Цепной пес (2005)",
      "film_href": "https:/www.kinopoisk.ru/film/6059/"
    },
    {
      "film_name": "13-й район (2004)",
      "film_href": "https:/www.kinopoisk.ru/film/81522/"
    },
    {
      "film_name": "Нью-Йоркское такси (2004)",
      "film_href": "https:/www.kinopoisk.ru/film/14330/"
    },
    {
      "film_name": "Точная копия (2004)",
      "film_href": "https:/www.kinopoisk.ru/film/14334/"
    },
    {
      "film_name": "Багровые реки 2: Ангелы апокалипсиса (2004)",
      "film_href": "https:/www.kinopoisk.ru/film/5621/"
    },
    {
      "film_name": "Мишель Вальян: Жажда скорости (2003)",
      "film_href": "https:/www.kinopoisk.ru/film/14333/"
    },
    {
      "film_name": "Онг Бак (2003)",
      "film_href": "https:/www.kinopoisk.ru/film/50534/"
    },
    {
      "film_name": "Нахал (2003)",
      "film_href": "https:/www.kinopoisk.ru/film/14331/"
    },
    {
      "film_name": "Ноль один (2003)",
      "film_href": "https:/www.kinopoisk.ru/film/530408/"
    },
    {
      "film_name": "Отбивные (2003)",
      "film_href": "https:/www.kinopoisk.ru/film/14335/"
    },
    {
      "film_name": "Фанфан-тюльпан (2003)",
      "film_href": "https:/www.kinopoisk.ru/film/14336/"
    },
    {
      "film_name": "Я, Цезарь (2003)",
      "film_href": "https:/www.kinopoisk.ru/film/14338/"
    },
    {
      "film_name": "Такси 3 (2003)",
      "film_href": "https:/www.kinopoisk.ru/film/14339/"
    },
    {
      "film_name": "Смех и наказание (2003)",
      "film_href": "https:/www.kinopoisk.ru/film/14340/"
    },
    {
      "film_name": "Перевозчик (2002)",
      "film_href": "https:/www.kinopoisk.ru/film/6206/"
    },
    {
      "film_name": "Бланш (2002)",
      "film_href": "https:/www.kinopoisk.ru/film/14342/"
    },
    {
      "film_name": "Васаби (2001)",
      "film_href": "https:/www.kinopoisk.ru/film/14288/"
    },
    {
      "film_name": "Поцелуй дракона (2001)",
      "film_href": "https:/www.kinopoisk.ru/film/727/"
    },
    {
      "film_name": "15 августа (2001)",
      "film_href": "https:/www.kinopoisk.ru/film/14345/"
    },
    {
      "film_name": "Выход (2000)",
      "film_href": "https:/www.kinopoisk.ru/film/14347/"
    },
    {
      "film_name": "Дансер (2000)",
      "film_href": "https:/www.kinopoisk.ru/film/14348/"
    },
    {
      "film_name": "Такси 2 (2000)",
      "film_href": "https:/www.kinopoisk.ru/film/854/"
    },
    {
      "film_name": "Жанна д'Арк (1999)",
      "film_href": "https:/www.kinopoisk.ru/film/4513/"
    },
    {
      "film_name": "Такси (1998)",
      "film_href": "https:/www.kinopoisk.ru/film/14349/"
    },
    {
      "film_name": "Не глотать (1997)",
      "film_href": "https:/www.kinopoisk.ru/film/6735/"
    },
    {
      "film_name": "Леон (1994)",
      "film_href": "https:/www.kinopoisk.ru/film/389/"
    },
    {
      "film_name": "Львенок (1993)",
      "film_href": "https:/www.kinopoisk.ru/film/14350/"
    },
    {
      "film_name": "Arrête ton cinéma (1992)",
      "film_href": "https:/www.kinopoisk.ru/film/682670/"
    },
    {
      "film_name": "Атлантис (1991)",
      "film_href": "https:/www.kinopoisk.ru/film/14352/"
    },
    {
      "film_name": "Холодная луна (1991)",
      "film_href": "https:/www.kinopoisk.ru/film/14353/"
    },
    {
      "film_name": "Никита (1990)",
      "film_href": "https:/www.kinopoisk.ru/film/14301/"
    },
    {
      "film_name": "Голубая бездна (1988)",
      "film_href": "https:/www.kinopoisk.ru/film/9579/"
    },
    {
      "film_name": "Камикадзе (1986)",
      "film_href": "https:/www.kinopoisk.ru/film/14354/"
    },
    {
      "film_name": "Подземка (1985)",
      "film_href": "https:/www.kinopoisk.ru/film/14305/"
    },
    {
      "film_name": "Создание фильма «Подземка» (видео, 1985)",
      "film_href": "https:/www.kinopoisk.ru/film/517995/"
    },
    {
      "film_name": "Не бросайте трубку (1984)",
      "film_href": "https:/www.kinopoisk.ru/film/102197/"
    },
    {
      "film_name": "Последняя битва (1983)",
      "film_href": "https:/www.kinopoisk.ru/film/14311/"
    },
    {
      "film_name": "Предпоследний (1981)",
      "film_href": "https:/www.kinopoisk.ru/film/14313/"
    }
  ]
}