{
  "actor_name": "Никита Михалков",
  "actor_href": "https://www.kinopoisk.ru/name/101749/",
  "films": [
    {
      "film_name": "Утомленные солнцем 2 (сериал, 2011)",
      "film_href": "https:/www.kinopoisk.ru/series/652871/"
    },
    {
      "film_name": "Утомленные солнцем 2: Цитадель (2011)",
      "film_href": "https:/www.kinopoisk.ru/film/481101/"
    },
    {
      "film_name": "Утомленные солнцем 2: Предстояние (2010)",
      "film_href": "https:/www.kinopoisk.ru/film/103299/"
    },
    {
      "film_name": "12 (мини-сериал, 2007)",
      "film_href": "https:/www.kinopoisk.ru/series/542437/"
    },
    {
      "film_name": "Тупой жирный заяц (2007)",
      "film_href": "https:/www.kinopoisk.ru/film/271975/"
    },
    {
      "film_name": "12 (2007)",
      "film_href": "https:/www.kinopoisk.ru/film/222809/"
    },
    {
      "film_name": "Мне не больно (2006)",
      "film_href": "https:/www.kinopoisk.ru/film/178722/"
    },
    {
      "film_name": "Паломничество в Вечный город (мини-сериал, 2005)",
      "film_href": "https:/www.kinopoisk.ru/series/438230/"
    },
    {
      "film_name": "Статский советник (мини-сериал, 2005)",
      "film_href": "https:/www.kinopoisk.ru/series/1331276/"
    },
    {
      "film_name": "Персона нон грата (2005)",
      "film_href": "https:/www.kinopoisk.ru/film/160937/"
    },
    {
      "film_name": "Жмурки (2005)",
      "film_href": "https:/www.kinopoisk.ru/film/84830/"
    },
    {
      "film_name": "Статский советник (2005)",
      "film_href": "https:/www.kinopoisk.ru/film/94111/"
    },
    {
      "film_name": "Вера, надежда, кровь (2000)",
      "film_href": "https:/www.kinopoisk.ru/film/28242/"
    },
    {
      "film_name": "Воспоминания о Шерлоке Холмсе (сериал, 2000)",
      "film_href": "https:/www.kinopoisk.ru/series/456501/"
    },
    {
      "film_name": "Сибирский цирюльник (1998)",
      "film_href": "https:/www.kinopoisk.ru/film/16445/"
    },
    {
      "film_name": "Ревизор (1996)",
      "film_href": "https:/www.kinopoisk.ru/film/40711/"
    },
    {
      "film_name": "Утомленные солнцем (1994)",
      "film_href": "https:/www.kinopoisk.ru/film/40848/"
    },
    {
      "film_name": "Тихий Дон (сериал, 1992 – 2006)",
      "film_href": "https:/www.kinopoisk.ru/series/77842/"
    },
    {
      "film_name": "Прекрасная незнакомка (1992)",
      "film_href": "https:/www.kinopoisk.ru/film/40894/"
    },
    {
      "film_name": "Униженные и оскорбленные (1990)",
      "film_href": "https:/www.kinopoisk.ru/film/29775/"
    },
    {
      "film_name": "Под северным сиянием (1990)",
      "film_href": "https:/www.kinopoisk.ru/film/43036/"
    },
    {
      "film_name": "Жестокий романс (1984)",
      "film_href": "https:/www.kinopoisk.ru/film/45314/"
    },
    {
      "film_name": "250 грамм. Радиоактивное заражение (1983)",
      "film_href": "https:/www.kinopoisk.ru/film/64930/"
    },
    {
      "film_name": "Инспектор ГАИ (1982)",
      "film_href": "https:/www.kinopoisk.ru/film/42608/"
    },
    {
      "film_name": "Вокзал для двоих (1982)",
      "film_href": "https:/www.kinopoisk.ru/film/45822/"
    },
    {
      "film_name": "Полеты во сне и наяву (1982)",
      "film_href": "https:/www.kinopoisk.ru/film/43114/"
    },
    {
      "film_name": "Портрет жены художника (1982)",
      "film_href": "https:/www.kinopoisk.ru/film/43132/"
    },
    {
      "film_name": "Два голоса (ТВ, 1981)",
      "film_href": "https:/www.kinopoisk.ru/film/94951/"
    },
    {
      "film_name": "Родня (1981)",
      "film_href": "https:/www.kinopoisk.ru/film/42115/"
    },
    {
      "film_name": "Приключения Шерлока Холмса и доктора Ватсона: Собака Баскервилей (ТВ, 1981)",
      "film_href": "https:/www.kinopoisk.ru/film/77263/"
    },
    {
      "film_name": "Сибириада (мини-сериал, 1978)",
      "film_href": "https:/www.kinopoisk.ru/series/43783/"
    },
    {
      "film_name": "Неоконченная пьеса для механического пианино (1976)",
      "film_href": "https:/www.kinopoisk.ru/film/46398/"
    },
    {
      "film_name": "Раба любви (1975)",
      "film_href": "https:/www.kinopoisk.ru/film/42030/"
    },
    {
      "film_name": "Свой среди чужих, чужой среди своих (1974)",
      "film_href": "https:/www.kinopoisk.ru/film/44062/"
    },
    {
      "film_name": "Станционный смотритель (ТВ, 1972)",
      "film_href": "https:/www.kinopoisk.ru/film/85021/"
    },
    {
      "film_name": "Держись за облака (1971)",
      "film_href": "https:/www.kinopoisk.ru/film/44152/"
    },
    {
      "film_name": "Спорт, спорт, спорт (1970)",
      "film_href": "https:/www.kinopoisk.ru/film/43947/"
    },
    {
      "film_name": "Песнь о Маншук (1969)",
      "film_href": "https:/www.kinopoisk.ru/film/42957/"
    },
    {
      "film_name": "Красная палатка (1969)",
      "film_href": "https:/www.kinopoisk.ru/film/13521/"
    },
    {
      "film_name": "Дворянское гнездо (1969)",
      "film_href": "https:/www.kinopoisk.ru/film/44359/"
    },
    {
      "film_name": "Звезды и солдаты (1967)",
      "film_href": "https:/www.kinopoisk.ru/film/45580/"
    },
    {
      "film_name": "Не самый удачный день (1966)",
      "film_href": "https:/www.kinopoisk.ru/film/46370/"
    },
    {
      "film_name": "Шуточка (ТВ, 1966)",
      "film_href": "https:/www.kinopoisk.ru/film/331782/"
    },
    {
      "film_name": "Перекличка (1966)",
      "film_href": "https:/www.kinopoisk.ru/film/42923/"
    },
    {
      "film_name": "Год как жизнь (1966)",
      "film_href": "https:/www.kinopoisk.ru/film/44523/"
    },
    {
      "film_name": "Война и мир: Андрей Болконский (1965)",
      "film_href": "https:/www.kinopoisk.ru/film/45817/"
    },
    {
      "film_name": "Война и мир (1965)",
      "film_href": "https:/www.kinopoisk.ru/film/38898/"
    },
    {
      "film_name": "Я шагаю по Москве (1963)",
      "film_href": "https:/www.kinopoisk.ru/film/42398/"
    },
    {
      "film_name": "Приключения Кроша (1962)",
      "film_href": "https:/www.kinopoisk.ru/film/43255/"
    },
    {
      "film_name": "Тучи над Борском (1961)",
      "film_href": "https:/www.kinopoisk.ru/film/42364/"
    },
    {
      "film_name": "Солнце светит всем (1959)",
      "film_href": "https:/www.kinopoisk.ru/film/43905/"
    }
  ]
}